codecision/__init__.py
codecision-0.0.0.dist-info/LICENSE
codecision-0.0.0.dist-info/METADATA
codecision-0.0.0.dist-info/WHEEL
codecision-0.0.0.dist-info/top_level.txt
codecision-0.0.0.dist-info/RECORD
